README.rst
setup.cfg
setup.py
argspander/__init__.py
argspander.egg-info/PKG-INFO
argspander.egg-info/SOURCES.txt
argspander.egg-info/dependency_links.txt
argspander.egg-info/not-zip-safe
argspander.egg-info/top_level.txt
argspander/tests/__init__.py
argspander/tests/test_argspander.py