Metadata-Version: 1.1
Name: argspander
Version: 0.1.3
Summary: Argument expansion of objects
Home-page: UNKNOWN
Author: Richard Lancaster
Author-email: lancasterrich@gmail.com
License: MIT
Keywords: expansion splat argument unpacking
Platform: UNKNOWN
Classifier: Development Status :: 3 - Alpha
Classifier: Intended Audience :: Developers
Classifier: License :: OSI Approved :: MIT License
Classifier: Programming Language :: Python :: 2.7
Classifier: Programming Language :: Python :: 3.4
